word_review_parser/__init__.py
word_review_parser/core.py
word_review_parser/latex_parser.py
word_review_parser/models.py
word_review_parser/word_builder.py
word_review_parser-1.0.3.dist-info/licenses/LICENSE
word_review_parser-1.0.3.dist-info/METADATA
word_review_parser-1.0.3.dist-info/WHEEL
word_review_parser-1.0.3.dist-info/top_level.txt
word_review_parser-1.0.3.dist-info/RECORD
