Metadata-Version: 2.4
Name: word-review-parser
Version: 1.0.3
Summary: 带有修订的docx文档 <-> 带有changes标记的tex文件
Author-email: VerNe <yuu_seeing@foxmail.com>
Project-URL: Homepage, https://github.com/ID-VerNe/docx2tex
Project-URL: Bug Tracker, https://github.com/ID-VerNe/docx2tex/issues
Classifier: Programming Language :: Python :: 3
Classifier: License :: OSI Approved :: MIT License
Classifier: Operating System :: OS Independent
Requires-Python: >=3.8
License-File: LICENSE
Requires-Dist: python-docx
Requires-Dist: lxml
Dynamic: license-file
